valkit/__init__.py
valkit/common.py
valkit/extra.py
valkit/fs.py
valkit/network.py
valkit/python.py
valkit/unix.py
valkit-0.1.4.dist-info/METADATA
valkit-0.1.4.dist-info/WHEEL
valkit-0.1.4.dist-info/top_level.txt
valkit-0.1.4.dist-info/RECORD
