Metadata-Version: 1.1
Name: valkit
Version: 0.1.4
Summary: Yet another Python validators
Home-page: https://github.com/mdevaev/valkit
Author: Devaev Maxim
Author-email: mdevaev@gmail.com
License: LGPLv3
Platform: any
Classifier: Development Status :: 4 - Beta
Classifier: License :: OSI Approved :: GNU Lesser General Public License v3 (LGPLv3)
Classifier: Programming Language :: Python :: 3
Classifier: Topic :: Software Development :: Libraries :: Python Modules
